nvd_client/__init__.py
nvd_client/api.py
nvd_client/exceptions.py
nvd_client/utils.py
nvd_client-1.2.6.dist-info/LICENSE
nvd_client-1.2.6.dist-info/METADATA
nvd_client-1.2.6.dist-info/WHEEL
nvd_client-1.2.6.dist-info/top_level.txt
nvd_client-1.2.6.dist-info/RECORD
