Metadata-Version: 2.1
Name: nvd-client
Version: 1.2.6
Summary: A Python client for interacting with the National Vulnerability Database (NVD) API to fetch CVE data.
Home-page: https://github.com/ahur4/nvd-client
Author: Ahur4
Author-email: ahur4.rahmani@gmail.com
Keywords: vulnerability,nvd,national vulnerability database,nvd_client,nvd_client-api,ahur4,ahura rahmani,redteam,soc,vulnerability assessment,penetration testing
Classifier: Programming Language :: Python :: 3
Classifier: License :: OSI Approved :: MIT License
Classifier: Operating System :: OS Independent
Requires-Python: >=3.6
License-File: LICENSE
Requires-Dist: certifi ==2024.6.2
Requires-Dist: charset-normalizer ==3.3.2
Requires-Dist: idna ==3.7
Requires-Dist: requests[socks] ==2.32.3
Requires-Dist: urllib3 ==2.2.1
